number_guessing_game/__init__.py
number_guessing_game/game.py
number_guessing_game_bhimesh-1.0.3.dist-info/licenses/LICENSE
number_guessing_game_bhimesh-1.0.3.dist-info/METADATA
number_guessing_game_bhimesh-1.0.3.dist-info/WHEEL
number_guessing_game_bhimesh-1.0.3.dist-info/entry_points.txt
number_guessing_game_bhimesh-1.0.3.dist-info/top_level.txt
number_guessing_game_bhimesh-1.0.3.dist-info/RECORD
