Metadata-Version: 2.4
Name: number-guessing-game-bhimesh
Version: 1.0.3
Summary: An interactive number guessing game where players try to guess a random number between 1 and 100
Home-page: https://github.com/yourusername/number-guessing-game
Author: bhimesh
Author-email: Bhimesh <bhimesh@example.com>
License: MIT
Project-URL: Homepage, https://github.com/bhimesh/number-guessing-game
Project-URL: Repository, https://github.com/bhimesh/number-guessing-game
Project-URL: Issues, https://github.com/bhimesh/number-guessing-game/issues
Keywords: game,guessing,interactive,entertainment
Classifier: Development Status :: 4 - Beta
Classifier: Intended Audience :: End Users/Desktop
Classifier: License :: OSI Approved :: MIT License
Classifier: Programming Language :: Python :: 3
Classifier: Programming Language :: Python :: 3.6
Classifier: Programming Language :: Python :: 3.7
Classifier: Programming Language :: Python :: 3.8
Classifier: Programming Language :: Python :: 3.9
Classifier: Programming Language :: Python :: 3.10
Classifier: Programming Language :: Python :: 3.11
Classifier: Topic :: Games/Entertainment
Requires-Python: >=3.6
License-File: LICENSE
Dynamic: author
Dynamic: home-page
Dynamic: license-file
Dynamic: requires-python
